{"tags":[],"display":"wizard","name":"Søknad om utbetaling av omsorgspenger for selvstendig næringsdrivende og frilansere","type":"form","id":280,"revision":12,"skjemanummer":"NAV 09-06.01","path":"nav090601","title":"Søknad om utbetaling av omsorgspenger for selvstendig næringsdrivende og frilansere","components":[{"id":"e5e9l2","key":"personopplysninger","tree":false,"type":"panel","input":false,"label":"Panel","navId":"ec24gf1","theme":"default","title":"Dine opplysninger","addons":[],"hidden":false,"prefix":"","suffix":"","unique":false,"dbIndex":false,"overlay":{"top":"","left":"","style":"","width":"","height":""},"tooltip":"","disabled":false,"lazyLoad":false,"multiple":false,"redrawOn":"","tabindex":"","validate":{"custom":"","unique":false,"multiple":false,"required":false,"customPrivate":false,"strictDateValidation":false},"autofocus":false,"encrypted":false,"hideLabel":false,"modalEdit":false,"protected":false,"refreshOn":"","tableView":false,"attributes":{},"breadcrumb":"default","components":[{"id":"esgdun","key":"dineOpplysninger","tree":true,"type":"container","input":true,"label":"Dine opplysninger","navId":"e9m32zi","addons":[],"hidden":false,"prefix":"","suffix":"","unique":false,"dbIndex":false,"overlay":{"top":"","left":"","style":"","width":"","height":""},"tooltip":"","disabled":false,"lazyLoad":false,"multiple":false,"redrawOn":"","tabindex":"","validate":{"custom":"","unique":false,"multiple":false,"required":false,"customPrivate":false,"strictDateValidation":false},"autofocus":false,"encrypted":false,"hideLabel":true,"modalEdit":false,"protected":false,"refreshOn":"","tableView":false,"attributes":{},"components":[{"id":"enb6rzs","key":"fornavn","type":"firstName","input":true,"label":"Fornavn","navId":"e8dlqls","addons":[],"hidden":false,"prefix":"","suffix":"","unique":false,"dbIndex":false,"overlay":{"top":"","left":"","style":"","width":"","height":""},"prefill":true,"tooltip":"","disabled":false,"multiple":false,"redrawOn":"","tabindex":"","validate":{"custom":"","unique":false,"multiple":false,"required":true,"customPrivate":false,"strictDateValidation":false},"autofocus":false,"encrypted":false,"fieldSize":"input--xxl","hideLabel":false,"modalEdit":false,"protected":false,"refreshOn":"","tableView":false,"attributes":{},"errorLabel":"","persistent":true,"prefillKey":"sokerFornavn","properties":{},"validateOn":"blur","clearOnHide":true,"conditional":{"eq":""},"customClass":"","description":"","placeholder":"","autocomplete":"given-name","dataGridLabel":false,"labelPosition":"top","showCharCount":false,"showWordCount":false,"calculateValue":"","calculateServer":false,"protectedApiKey":true,"allowMultipleMasks":false,"customDefaultValue":"","allowCalculateOverride":false},{"id":"e9asmja","key":"etternavn","type":"surname","input":true,"label":"Etternavn","navId":"e2vsrii","addons":[],"hidden":false,"prefix":"","suffix":"","unique":false,"dbIndex":false,"overlay":{"top":"","left":"","style":"","width":"","height":""},"prefill":true,"tooltip":"","disabled":false,"multiple":false,"redrawOn":"","tabindex":"","validate":{"custom":"","unique":false,"multiple":false,"required":true,"customPrivate":false,"strictDateValidation":false},"autofocus":false,"encrypted":false,"fieldSize":"input--xxl","hideLabel":false,"modalEdit":false,"protected":false,"refreshOn":"","tableView":false,"attributes":{},"errorLabel":"","persistent":true,"prefillKey":"sokerEtternavn","properties":{},"validateOn":"blur","clearOnHide":true,"conditional":{"eq":""},"customClass":"","description":"","placeholder":"","autocomplete":"family-name","dataGridLabel":false,"labelPosition":"top","showCharCount":false,"showWordCount":false,"calculateValue":"","calculateServer":false,"protectedApiKey":true,"allowMultipleMasks":false,"customDefaultValue":"","allowCalculateOverride":false},{"id":"eenab8b","key":"identitet","type":"identity","input":true,"label":"Identitet","navId":"edzj1w6","addons":[],"hidden":false,"prefix":"","suffix":"","unique":false,"dbIndex":false,"overlay":{"top":"","left":"","style":"","width":"","height":""},"prefill":true,"tooltip":"","disabled":false,"multiple":false,"redrawOn":"","tabindex":"","validate":{"custom":"","unique":false,"multiple":false,"required":true,"customPrivate":false,"strictDateValidation":false},"autofocus":false,"encrypted":false,"fieldSize":"input--s","hideLabel":true,"modalEdit":false,"protected":false,"refreshOn":"","tableView":false,"attributes":{},"errorLabel":"","persistent":true,"prefillKey":"sokerIdentifikasjonsnummer","properties":{},"spellcheck":false,"validateOn":"blur","clearOnHide":true,"conditional":{"eq":""},"customClass":"","description":"","placeholder":"","customLabels":{"doYouHaveIdentityNumber":"Har du norsk fødselsnummer eller d-nummer?"},"dataGridLabel":false,"labelPosition":"top","showCharCount":false,"showWordCount":false,"calculateValue":"","calculateServer":false,"protectedApiKey":true,"allowMultipleMasks":false,"customDefaultValue":"","allowCalculateOverride":false},{"id":"etndqwd","key":"adresse","type":"navAddress","input":true,"label":"Adresse","navId":"ee51qs","addons":[],"hidden":false,"prefix":"","suffix":"","unique":false,"dbIndex":false,"overlay":{"top":"","left":"","style":"","width":"","height":""},"prefill":true,"tooltip":"","disabled":false,"multiple":false,"redrawOn":"","tabindex":"","validate":{"custom":"","unique":false,"multiple":false,"required":true,"customPrivate":false,"strictDateValidation":false},"autofocus":false,"encrypted":false,"fieldSize":"input--xxl","hideLabel":true,"modalEdit":false,"protected":false,"refreshOn":"","tableView":false,"attributes":{},"errorLabel":"","persistent":true,"prefillKey":"sokerAdresser","properties":{},"validateOn":"blur","clearOnHide":true,"conditional":{"eq":""},"customClass":"","description":"","placeholder":"","customLabels":{"livesInNorway":"Bor du i Norge?"},"dataGridLabel":false,"labelPosition":"top","showCharCount":false,"showWordCount":false,"calculateValue":"","calculateServer":false,"protectedApiKey":true,"customConditional":"show = row.identitet.harDuFodselsnummer === \"nei\" || (row.identitet.identitetsnummer && !row.identitet.harDuFodselsnummer)","allowMultipleMasks":false,"customDefaultValue":"","allowCalculateOverride":false},{"id":"eu9vrtm","key":"adresseVarighet","type":"addressValidity","input":true,"label":"Adresse varighet","navId":"el8ame7d","addons":[],"hidden":false,"prefix":"","suffix":"","unique":false,"dbIndex":false,"overlay":{"top":"","left":"","style":"","width":"","height":""},"tooltip":"","disabled":false,"multiple":false,"redrawOn":"","tabindex":"","validate":{"custom":"","unique":false,"multiple":false,"required":true,"customPrivate":false,"strictDateValidation":false},"autofocus":false,"encrypted":false,"fieldSize":"input--s","hideLabel":true,"modalEdit":false,"protected":false,"refreshOn":"","tableView":false,"attributes":{},"errorLabel":"","persistent":true,"properties":{},"validateOn":"blur","clearOnHide":true,"conditional":{"eq":""},"customClass":"","description":"","placeholder":"","dataGridLabel":false,"labelPosition":"top","showCharCount":false,"showWordCount":false,"calculateValue":"","calculateServer":false,"protectedApiKey":true,"customConditional":"show = row.adresse.borDuINorge === \"nei\" || (row.adresse.borDuINorge === \"ja\" && row.adresse.vegadresseEllerPostboksadresse)","allowMultipleMasks":false,"customDefaultValue":"","allowCalculateOverride":false},{"id":"elo2fz5","key":"alertstripe","type":"alertstripe","input":false,"label":"Alertstripe","navId":"egjb9ve","addons":[],"hidden":false,"prefix":"","suffix":"","unique":false,"content":"<p>Nav sender svar på søknad og annen kommunikasjon til din folkeregistrerte adresse. Du kan <a href=\"https://www.skatteetaten.no/person/folkeregister/flytte/endre-postadresse/\" target=\"_blank\" rel=\"noopener noreferrer\">sjekke og endre din folkeregistrerte adresse på Skatteetatens nettsider (åpnes i ny fane)</a>.</p>","dbIndex":false,"overlay":{"top":"","left":"","style":"","width":"","height":""},"tooltip":"","disabled":false,"multiple":false,"redrawOn":"","tabindex":"","validate":{"custom":"","unique":false,"multiple":false,"required":false,"customPrivate":false,"strictDateValidation":false},"alerttype":"info","autofocus":false,"encrypted":false,"hideLabel":true,"modalEdit":false,"protected":false,"refreshOn":"","tableView":false,"attributes":{},"errorLabel":"","persistent":true,"properties":{},"validateOn":"change","clearOnHide":true,"conditional":{"eq":""},"customClass":"","description":"","placeholder":"","dataGridLabel":false,"labelPosition":"top","showCharCount":false,"showWordCount":false,"calculateValue":"","calculateServer":false,"customConditional":"show = row.identitet.harDuFodselsnummer === \"ja\"","allowMultipleMasks":false,"customDefaultValue":"","allowCalculateOverride":false},{"id":"ez754fu","key":"alertstripePrefill","type":"alertstripe","input":false,"label":"Alertstripe","navId":"evmpbb","addons":[],"hidden":false,"prefix":"","suffix":"","unique":false,"content":"<p>Adressen er hentet fra Folkeregisteret. Du kan <a href=\"https://www.skatteetaten.no/person/folkeregister/flytte/endre-postadresse/\" target=\"_blank\" rel=\"noopener noreferrer\"> endre adressen på Skatteetatens nettsider (åpnes i ny fane)</a>.</p>","dbIndex":false,"overlay":{"top":"","left":"","style":"","width":"","height":""},"tooltip":"","disabled":false,"multiple":false,"redrawOn":"","tabindex":"","validate":{"custom":"","unique":false,"multiple":false,"required":false,"customPrivate":false,"strictDateValidation":false},"alerttype":"info","autofocus":false,"encrypted":false,"hideLabel":true,"modalEdit":false,"protected":false,"refreshOn":"","tableView":false,"attributes":{},"errorLabel":"","persistent":true,"properties":{},"validateOn":"change","clearOnHide":true,"conditional":{"eq":""},"customClass":"","description":"","placeholder":"","dataGridLabel":false,"labelPosition":"top","showCharCount":false,"showWordCount":false,"calculateValue":"","calculateServer":false,"customConditional":"show = row.identitet.identitetsnummer && !row.identitet.harDuFodselsnummer","allowMultipleMasks":false,"customDefaultValue":"","allowCalculateOverride":false}],"errorLabel":"","persistent":true,"properties":{},"validateOn":"change","clearOnHide":true,"conditional":{"eq":""},"customClass":"","description":"","placeholder":"","dataGridLabel":false,"labelPosition":"top","showCharCount":false,"showWordCount":false,"calculateValue":"","calculateServer":false,"yourInformation":true,"allowMultipleMasks":false,"customDefaultValue":"","allowCalculateOverride":false}],"errorLabel":"","persistent":false,"properties":{},"validateOn":"change","clearOnHide":false,"conditional":{"eq":""},"customClass":"","description":"","placeholder":"","dataGridLabel":false,"labelPosition":"top","showCharCount":false,"showWordCount":false,"calculateValue":"","calculateServer":false,"allowMultipleMasks":false,"customDefaultValue":"","allowCalculateOverride":false},{"id":"et5e7oj","key":"vedlegg","tree":false,"type":"panel","input":false,"label":"Panel","navId":"e6jdaf","theme":"default","title":"Vedlegg","addons":[],"hidden":false,"prefix":"","suffix":"","unique":false,"dbIndex":false,"overlay":{"top":"","left":"","style":"","width":"","height":""},"tooltip":"","disabled":false,"lazyLoad":false,"multiple":false,"redrawOn":"","tabindex":"","validate":{"custom":"","unique":false,"multiple":false,"required":false,"customPrivate":false,"strictDateValidation":false},"autofocus":false,"encrypted":false,"hideLabel":false,"modalEdit":false,"protected":false,"refreshOn":"","tableView":false,"attributes":{},"breadcrumb":"default","components":[{"id":"eayxc6","key":"legeerklaeringFraDen4DagenISammenhengendePerioder","type":"attachment","input":true,"label":"Legeerklæring fra den 4 dagen i sammenhengende perioder","navId":"e216xf","addons":[],"hidden":false,"prefix":"","suffix":"","unique":false,"dataSrc":"values","dbIndex":false,"overlay":{"top":"","left":"","style":"","width":"","height":""},"tooltip":"","disabled":false,"multiple":false,"redrawOn":"","tabindex":"","validate":{"custom":"","unique":false,"multiple":false,"required":true,"customPrivate":false,"strictDateValidation":false},"autofocus":false,"encrypted":false,"fieldSize":"input--xxl","hideLabel":false,"modalEdit":false,"protected":false,"refreshOn":"","tableView":false,"attributes":{},"errorLabel":"","persistent":true,"properties":{"vedleggskode":"L9","vedleggstittel":"Legeerklæring"},"validateOn":"blur","clearOnHide":true,"conditional":{"eq":""},"customClass":"","description":"","placeholder":"","dataGridLabel":false,"labelPosition":"top","showCharCount":false,"showWordCount":false,"attachmentType":"default","calculateValue":"","calculateServer":false,"attachmentValues":{"nav":{"enabled":false,"additionalDocumentation":{}},"andre":{"enabled":false,"additionalDocumentation":{}},"harIkke":{"enabled":false,"additionalDocumentation":{}},"ettersender":{"enabled":true,"showDeadline":false,"additionalDocumentation":{"enabled":false}},"leggerVedNaa":{"enabled":true,"additionalDocumentation":{"enabled":false}},"levertTidligere":{"enabled":true,"additionalDocumentation":{"enabled":false}}},"customConditional":"","allowMultipleMasks":false,"customDefaultValue":"","allowCalculateOverride":false,"additionalDescriptionText":"","additionalDescriptionLabel":""},{"id":"egn94v","key":"annenDokumentasjon","type":"attachment","input":true,"label":"Annen dokumentasjon","navId":"efq37rm","addons":[],"hidden":false,"prefix":"","suffix":"","unique":false,"dataSrc":"values","dbIndex":false,"overlay":{"top":"","left":"","style":"","width":"","height":""},"tooltip":"","disabled":false,"multiple":false,"redrawOn":"","tabindex":"","validate":{"custom":"","unique":false,"multiple":false,"required":true,"customPrivate":false,"strictDateValidation":false},"autofocus":false,"encrypted":false,"fieldSize":"input--xxl","hideLabel":false,"modalEdit":false,"protected":false,"refreshOn":"","tableView":false,"attributes":{},"errorLabel":"","persistent":true,"properties":{"vedleggskode":"N6","vedleggstittel":"Annet"},"validateOn":"blur","clearOnHide":true,"conditional":{"eq":""},"customClass":"","description":"Har du noen annen dokumentasjon du ønsker å legge ved?","placeholder":"","dataGridLabel":false,"labelPosition":"top","showCharCount":false,"showWordCount":false,"attachmentType":"other","calculateValue":"","calculateServer":false,"attachmentValues":{"nei":{"enabled":true},"leggerVedNaa":{"enabled":true}},"allowMultipleMasks":false,"customDefaultValue":"","allowCalculateOverride":false}],"errorLabel":"","persistent":false,"properties":{},"validateOn":"change","clearOnHide":false,"conditional":{"eq":""},"customClass":"","description":"","placeholder":"","dataGridLabel":false,"labelPosition":"top","showCharCount":false,"showWordCount":false,"calculateValue":"","calculateServer":false,"isAttachmentPanel":true,"allowMultipleMasks":false,"customDefaultValue":"","allowCalculateOverride":false}],"properties":{"tema":"OMS","signatures":[{"key":"d15464b3-d6c2-4e96-8b78-24806c8a384a","label":"","description":""}],"skjemanummer":"NAV 09-06.01","submissionTypes":["PAPER_NO_COVER_PAGE","STATIC_PDF"],"ettersendelsesfrist":"14","innsendingForklaring":"Du må laste ned og skrive ut skjemaet før du kan sende det i posten.","innsendingOverskrift":"Innsending","mellomlagringDurationDays":"28","subsequentSubmissionTypes":["PAPER","DIGITAL"],"publishedLanguages":["nn","nb"]},"createdAt":"2026-04-14T12:43:46.224+02","createdBy":"Rosseland, Rune","changedAt":"2026-06-29T12:32:08.556+02","changedBy":"Haslund, Christian","publishedAt":"2026-06-29T12:32:14.657+02","publishedBy":"Haslund, Christian","publicationId":"pub_01kw9ezmjwet9a05ntd26tq85n","publishedLanguages":["nn","nb"],"status":"published","firstPanelSlug":""}